netunicorn/director/infrastructure/connectors/containernet/__init__.py
netunicorn/director/infrastructure/connectors/containernet/connector.py
netunicorn/director/infrastructure/connectors/containernet/rest.py
netunicorn_connector_containernet-0.0.2.dist-info/LICENSE
netunicorn_connector_containernet-0.0.2.dist-info/METADATA
netunicorn_connector_containernet-0.0.2.dist-info/WHEEL
netunicorn_connector_containernet-0.0.2.dist-info/top_level.txt
netunicorn_connector_containernet-0.0.2.dist-info/RECORD
