Metadata-Version: 2.1
Name: netunicorn-connector-containernet
Version: 0.0.2
Summary: ContainerNet connector for netunicorn
Author-email: Roman Beltiukov <rbeltiukov@ucsb.edu>
License: MIT
Keywords: netunicorn
Classifier: Programming Language :: Python :: 3
Requires-Python: >=3.10
License-File: LICENSE
Requires-Dist: netunicorn-base >=0.3.3
Requires-Dist: pyyaml
Requires-Dist: docker
Requires-Dist: fastapi
Requires-Dist: uvicorn
